{
    "courses": [
        {
            "vetCode": "#AHC30716",
            "cricosCode": "110597F",
            "department": "HORTICULTURE",
            "name": "CERTIFICATE III IN HORTICULTURE",
            "duration": "52",
            "durationDetail": "44 wks Tuition + 8 wks Break",
            "tuition": "9,700",
            "tuitionDetail": "9,500 tuition fee + 200 handling fee",
            "location": "TAS",
            "note": "#This qualification has been superseded. For more information, please refer to Terms and Conditions at the back of the brochure",
            "promotionValidity": "PROMOTIONS VALID UNTIL 30TH JUNE 2023 "
        },
        {
            "vetCode": "#AHC40416",
            "cricosCode": "110598E",
            "department": "HORTICULTURE",
            "name": "CERTIFICATE IV IN HORTICULTURE",
            "duration": "52",
            "durationDetail": "44 wks Tuition + 8 wks Break",
            "tuition": "9,700",
            "tuitionDetail": "9,500 tuition fee + 200 handling fee",
            "location": "TAS",
            "note": "#This qualification has been superseded. For more information, please refer to Terms and Conditions at the back of the brochure",
            "promotionValidity": "PROMOTIONS VALID UNTIL 30TH JUNE 2023"
        },
        {
            "vetCode": "AHC51422",
            "cricosCode": "110774E",
            "department": "MANAGEMENT",
            "name": "DIPLOMA OF AGRIBUSINESS MANAGEMENT",
            "duration": "52",
            "durationDetail": "44 wks Tuition + 8 wks Break",
            "tuition": "10,200",
            "tuitionDetail": "10,000 tuition fee + 200 handling fee",
            "location": "TAS",
            "promotionValidity": "PROMOTIONS VALID UNTIL 30TH JUNE 2023"
        },
        {
            "vetCode": "#AHC30716 / #AHC40416",
            "cricosCode": "110597F / 110598E",
            "department": "PACKAGES",
            "name": "CERTIFICATE III IN HORTICULTURE + CERTIFICATE IV IN HORTICULTURE",
            "duration": "104",
            "durationDetail": "88 wks Tuition + 16 wks Break",
            "tuition": "17,700",
            "tuitionDetail": "17,500 tuition fee + 200 handling fee",
            "location": "TAS",
            "note": "#This qualification has been superseded. For more information, please refer to Terms and Conditions at the back of the brochure",
            "promotionValidity": "PROMOTIONS VALID UNTIL 30TH JUNE 2023 "
        },
        {
            "vetCode": "#AHC30716 / AHC51422",
            "cricosCode": "110597F / 110774E",
            "department": "PACKAGES",
            "name": "CERTIFICATE III IN HORTICULTURE + DIPLOMA OF AGRIBUSINESS MANAGEMENT",
            "duration": "104",
            "durationDetail": "88 wks Tuition + 16 wks Break",
            "tuition": "18,200",
            "tuitionDetail": "18,000 tuition fee + 200 handling fee",
            "location": "TAS",
            "note": "#This qualification has been superseded. For more information, please refer to Terms and Conditions at the back of the brochure",
            "promotionValidity": "PROMOTIONS VALID UNTIL 30TH JUNE 2023 "
        },
        {
            "vetCode": "#AHC40416 / AHC51422",
            "cricosCode": "110598E / 110774E",
            "department": "PACKAGES",
            "name": "CERTIFICATE IV IN HORTICULTURE + DIPLOMA OF AGRIBUSINESS MANAGEMENT",
            "duration": "104",
            "durationDetail": "88 wks Tuition + 16 wks Break",
            "tuition": "18,200",
            "tuitionDetail": "18,000 tuition fee + 200 handling fee",
            "location": "TAS",
            "note": "#This qualification has been superseded. For more information, please refer to Terms and Conditions at the back of the brochure",
            "promotionValidity": "PROMOTIONS VALID UNTIL 30TH JUNE 2023"
        }
    ]
}
